[
  {
    "category":"nicotine-vape",
    "slug":"nicotine-vape-product-1",
    "name":"Nicotine Vape Product 1",
    "description":"This is a detailed description of Nicotine Vape Product 1.",
    "image":"\/images\/nicotine-vape-product-1.jpg"
  },
  {
    "category":"nicotine-vape",
    "slug":"nicotine-vape-product-2",
    "name":"Nicotine Vape Product 2",
    "description":"This is a detailed description of Nicotine Vape Product 2.",
    "image":"\/images\/nicotine-vape-product-2.jpg"
  },
  {
    "category":"nicotine-vape",
    "slug":"nicotine-vape-product-3",
    "name":"Nicotine Vape Product 3",
    "description":"This is a detailed description of Nicotine Vape Product 3.",
    "image":"\/images\/nicotine-vape-product-3.jpg"
  },
  {
    "category":"nicotine-vape",
    "slug":"nicotine-vape-product-4",
    "name":"Nicotine Vape Product 4",
    "description":"This is a detailed description of Nicotine Vape Product 4.",
    "image":"\/images\/nicotine-vape-product-4.jpg"
  },
  {
    "category":"nicotine-vape",
    "slug":"nicotine-vape-product-5",
    "name":"Nicotine Vape Product 5",
    "description":"This is a detailed description of Nicotine Vape Product 5.",
    "image":"\/images\/nicotine-vape-product-5.jpg"
  },
  {
    "category":"nicotine-vape",
    "slug":"nicotine-vape-product-6",
    "name":"Nicotine Vape Product 6",
    "description":"This is a detailed description of Nicotine Vape Product 6.",
    "image":"\/images\/nicotine-vape-product-6.jpg"
  },
  {
    "category":"nicotine-vape",
    "slug":"nicotine-vape-product-7",
    "name":"Nicotine Vape Product 7",
    "description":"This is a detailed description of Nicotine Vape Product 7.",
    "image":"\/images\/nicotine-vape-product-7.jpg"
  },
  {
    "category":"nicotine-vape",
    "slug":"nicotine-vape-product-8",
    "name":"Nicotine Vape Product 8",
    "description":"This is a detailed description of Nicotine Vape Product 8.",
    "image":"\/images\/nicotine-vape-product-8.jpg"
  },
  {
    "category":"nicotine-vape",
    "slug":"nicotine-vape-product-9",
    "name":"Nicotine Vape Product 9",
    "description":"This is a detailed description of Nicotine Vape Product 9.",
    "image":"\/images\/nicotine-vape-product-9.jpg"
  },
  {
    "category":"nicotine-vape",
    "slug":"nicotine-vape-product-10",
    "name":"Nicotine Vape Product 10",
    "description":"This is a detailed description of Nicotine Vape Product 10.",
    "image":"\/images\/nicotine-vape-product-10.jpg"
  },
  {
    "category":"nicotine-vape",
    "slug":"nicotine-vape-product-11",
    "name":"Nicotine Vape Product 11",
    "description":"This is a detailed description of Nicotine Vape Product 11.",
    "image":"\/images\/nicotine-vape-product-11.jpg"
  },
  {
    "category":"nicotine-vape",
    "slug":"nicotine-vape-product-12",
    "name":"Nicotine Vape Product 12",
    "description":"This is a detailed description of Nicotine Vape Product 12.",
    "image":"\/images\/nicotine-vape-product-12.jpg"
  },
  {
    "category":"nicotine-vape",
    "slug":"nicotine-vape-product-13",
    "name":"Nicotine Vape Product 13",
    "description":"This is a detailed description of Nicotine Vape Product 13.",
    "image":"\/images\/nicotine-vape-product-13.jpg"
  },
  {
    "category":"nicotine-vape",
    "slug":"nicotine-vape-product-14",
    "name":"Nicotine Vape Product 14",
    "description":"This is a detailed description of Nicotine Vape Product 14.",
    "image":"\/images\/nicotine-vape-product-14.jpg"
  },
  {
    "category":"nicotine-vape",
    "slug":"nicotine-vape-product-15",
    "name":"Nicotine Vape Product 15",
    "description":"This is a detailed description of Nicotine Vape Product 15.",
    "image":"\/images\/nicotine-vape-product-15.jpg"
  },
  {
    "category":"nicotine-vape",
    "slug":"nicotine-vape-product-16",
    "name":"Nicotine Vape Product 16",
    "description":"This is a detailed description of Nicotine Vape Product 16.",
    "image":"\/images\/nicotine-vape-product-16.jpg"
  },
  {
    "category":"nicotine-vape",
    "slug":"nicotine-vape-product-17",
    "name":"Nicotine Vape Product 17",
    "description":"This is a detailed description of Nicotine Vape Product 17.",
    "image":"\/images\/nicotine-vape-product-17.jpg"
  },
  {
    "category":"nicotine-vape",
    "slug":"nicotine-vape-product-18",
    "name":"Nicotine Vape Product 18",
    "description":"This is a detailed description of Nicotine Vape Product 18.",
    "image":"\/images\/nicotine-vape-product-18.jpg"
  },
  {
    "category":"nicotine-vape",
    "slug":"nicotine-vape-product-19",
    "name":"Nicotine Vape Product 19",
    "description":"This is a detailed description of Nicotine Vape Product 19.",
    "image":"\/images\/nicotine-vape-product-19.jpg"
  },
  {
    "category":"nicotine-vape",
    "slug":"nicotine-vape-product-20",
    "name":"Nicotine Vape Product 20",
    "description":"This is a detailed description of Nicotine Vape Product 20.",
    "image":"\/images\/nicotine-vape-product-20.jpg"
  }
]